jajula_chunking/__init__.py
jajula_chunking/exceptions.py
jajula_chunking/chunkers/__init__.py
jajula_chunking/chunkers/adaptive.py
jajula_chunking/chunkers/base.py
jajula_chunking/chunkers/fixed_size.py
jajula_chunking/chunkers/hierarchical.py
jajula_chunking/chunkers/paragraph_based.py
jajula_chunking/chunkers/recursive.py
jajula_chunking/chunkers/semantic.py
jajula_chunking/chunkers/sentence_based.py
jajula_chunking/chunkers/structure_based.py
jajula_chunking/chunkers/token_based.py
jajula_chunking/utils/__init__.py
jajula_chunking/utils/text_processing.py
jajula_chunking/utils/validators.py
jajula_chunking-0.1.4.dist-info/licenses/LICENSE
jajula_chunking-0.1.4.dist-info/METADATA
jajula_chunking-0.1.4.dist-info/WHEEL
jajula_chunking-0.1.4.dist-info/top_level.txt
jajula_chunking-0.1.4.dist-info/RECORD
