Metadata-Version: 2.4
Name: jajula-chunking
Version: 0.1.4
Summary: A comprehensive text chunking library for RAG applications with multiple strategies
Author-email: Jajula <contact@jajula.com>
License: MIT
Project-URL: Homepage, https://github.com/jajula/jajula-chunking
Project-URL: Repository, https://github.com/jajula/jajula-chunking
Project-URL: Documentation, https://github.com/jajula/jajula-chunking#readme
Project-URL: Issues, https://github.com/jajula/jajula-chunking/issues
Keywords: chunking,rag,nlp,text-processing,ai,machine-learning
Classifier: Development Status :: 4 - Beta
Classifier: Intended Audience :: Developers
Classifier: Intended Audience :: Science/Research
Classifier: License :: OSI Approved :: MIT License
Classifier: Operating System :: OS Independent
Classifier: Programming Language :: Python :: 3
Classifier: Programming Language :: Python :: 3.8
Classifier: Programming Language :: Python :: 3.9
Classifier: Programming Language :: Python :: 3.10
Classifier: Programming Language :: Python :: 3.11
Classifier: Programming Language :: Python :: 3.12
Classifier: Topic :: Scientific/Engineering :: Artificial Intelligence
Classifier: Topic :: Text Processing :: Linguistic
Requires-Python: >=3.8
License-File: LICENSE
Requires-Dist: nltk>=3.8
Requires-Dist: beautifulsoup4>=4.11.0
Requires-Dist: numpy>=1.21.0
Requires-Dist: scikit-learn>=1.0.0
Requires-Dist: sentence-transformers>=2.2.0
Requires-Dist: tiktoken>=0.4.0
Requires-Dist: transformers>=4.21.0
Requires-Dist: torch>=1.12.0
Provides-Extra: dev
Requires-Dist: pytest>=7.0.0; extra == "dev"
Requires-Dist: pytest-cov>=4.0.0; extra == "dev"
Requires-Dist: black>=22.0.0; extra == "dev"
Requires-Dist: flake8>=5.0.0; extra == "dev"
Requires-Dist: mypy>=0.991; extra == "dev"
Requires-Dist: isort>=5.10.0; extra == "dev"
Requires-Dist: pre-commit>=2.20.0; extra == "dev"
Provides-Extra: docs
Requires-Dist: sphinx>=5.0.0; extra == "docs"
Requires-Dist: sphinx-rtd-theme>=1.0.0; extra == "docs"
Requires-Dist: myst-parser>=0.18.0; extra == "docs"
Dynamic: license-file
